{
  "cook according to recipe instruction": {
    "emoji": "📦",
    "name": "Cook according to recipe instructions",
    "normalizedName": "cook according to recipe instruction",
    "total": 0,
    "unit": "",
    "remaining": 0,
    "dailyUsage": [
      {
        "day": "Wednesday",
        "mealType": "breakfast",
        "amount": 0,
        "unit": "",
        "meal": "Rice noodles with egg"
      },
      {
        "day": "Wednesday",
        "mealType": "snack",
        "amount": 0,
        "unit": "",
        "meal": "Rice crackers"
      },
      {
        "day": "Wednesday",
        "mealType": "dinner",
        "amount": 0,
        "unit": "",
        "meal": "Beef stroganoff with rice"
      },
      {
        "day": "Thursday",
        "mealType": "breakfast",
        "amount": 0,
        "unit": "",
        "meal": "Fried eggs with bread"
      },
      {
        "day": "Thursday",
        "mealType": "snack",
        "amount": 0,
        "unit": "",
        "meal": "Mango slices"
      },
      {
        "day": "Thursday",
        "mealType": "dinner",
        "amount": 0,
        "unit": "",
        "meal": "Chicken soup with vegetables"
      },
      {
        "day": "Friday",
        "mealType": "breakfast",
        "amount": 0,
        "unit": "",
        "meal": "Blini with cheese filling"
      },
      {
        "day": "Friday",
        "mealType": "snack",
        "amount": 0,
        "unit": "",
        "meal": "Seaweed snacks"
      },
      {
        "day": "Friday",
        "mealType": "dinner",
        "amount": 0,
        "unit": "",
        "meal": "Korean bibimbap"
      },
      {
        "day": "Saturday",
        "mealType": "breakfast",
        "amount": 0,
        "unit": "",
        "meal": "Kasha with butter and milk"
      },
      {
        "day": "Saturday",
        "mealType": "snack",
        "amount": 0,
        "unit": "",
        "meal": "Banana with peanut butter"
      },
      {
        "day": "Saturday",
        "mealType": "dinner",
        "amount": 0,
        "unit": "",
        "meal": "Borscht with sour cream"
      }
    ]
  },
  "main ingredients vary by recipe": {
    "emoji": "📦",
    "name": "Main ingredients vary by recipe",
    "normalizedName": "main ingredients vary by recipe",
    "total": 0,
    "unit": "",
    "remaining": 0,
    "dailyUsage": [
      {
        "day": "Wednesday",
        "mealType": "breakfast",
        "amount": 0,
        "unit": "",
        "meal": "Rice noodles with egg"
      },
      {
        "day": "Wednesday",
        "mealType": "snack",
        "amount": 0,
        "unit": "",
        "meal": "Rice crackers"
      },
      {
        "day": "Wednesday",
        "mealType": "dinner",
        "amount": 0,
        "unit": "",
        "meal": "Beef stroganoff with rice"
      },
      {
        "day": "Thursday",
        "mealType": "breakfast",
        "amount": 0,
        "unit": "",
        "meal": "Fried eggs with bread"
      },
      {
        "day": "Thursday",
        "mealType": "snack",
        "amount": 0,
        "unit": "",
        "meal": "Mango slices"
      },
      {
        "day": "Thursday",
        "mealType": "dinner",
        "amount": 0,
        "unit": "",
        "meal": "Chicken soup with vegetables"
      },
      {
        "day": "Friday",
        "mealType": "breakfast",
        "amount": 0,
        "unit": "",
        "meal": "Blini with cheese filling"
      },
      {
        "day": "Friday",
        "mealType": "snack",
        "amount": 0,
        "unit": "",
        "meal": "Seaweed snacks"
      },
      {
        "day": "Friday",
        "mealType": "dinner",
        "amount": 0,
        "unit": "",
        "meal": "Korean bibimbap"
      },
      {
        "day": "Saturday",
        "mealType": "breakfast",
        "amount": 0,
        "unit": "",
        "meal": "Kasha with butter and milk"
      },
      {
        "day": "Saturday",
        "mealType": "snack",
        "amount": 0,
        "unit": "",
        "meal": "Banana with peanut butter"
      },
      {
        "day": "Saturday",
        "mealType": "dinner",
        "amount": 0,
        "unit": "",
        "meal": "Borscht with sour cream"
      }
    ]
  },
  "seasonings to taste": {
    "emoji": "📦",
    "name": "Seasonings to taste",
    "normalizedName": "seasonings to taste",
    "total": 0,
    "unit": "",
    "remaining": 0,
    "dailyUsage": [
      {
        "day": "Wednesday",
        "mealType": "breakfast",
        "amount": 0,
        "unit": "",
        "meal": "Rice noodles with egg"
      },
      {
        "day": "Wednesday",
        "mealType": "snack",
        "amount": 0,
        "unit": "",
        "meal": "Rice crackers"
      },
      {
        "day": "Wednesday",
        "mealType": "dinner",
        "amount": 0,
        "unit": "",
        "meal": "Beef stroganoff with rice"
      },
      {
        "day": "Thursday",
        "mealType": "breakfast",
        "amount": 0,
        "unit": "",
        "meal": "Fried eggs with bread"
      },
      {
        "day": "Thursday",
        "mealType": "snack",
        "amount": 0,
        "unit": "",
        "meal": "Mango slices"
      },
      {
        "day": "Thursday",
        "mealType": "dinner",
        "amount": 0,
        "unit": "",
        "meal": "Chicken soup with vegetables"
      },
      {
        "day": "Friday",
        "mealType": "breakfast",
        "amount": 0,
        "unit": "",
        "meal": "Blini with cheese filling"
      },
      {
        "day": "Friday",
        "mealType": "snack",
        "amount": 0,
        "unit": "",
        "meal": "Seaweed snacks"
      },
      {
        "day": "Friday",
        "mealType": "dinner",
        "amount": 0,
        "unit": "",
        "meal": "Korean bibimbap"
      },
      {
        "day": "Saturday",
        "mealType": "breakfast",
        "amount": 0,
        "unit": "",
        "meal": "Kasha with butter and milk"
      },
      {
        "day": "Saturday",
        "mealType": "snack",
        "amount": 0,
        "unit": "",
        "meal": "Banana with peanut butter"
      },
      {
        "day": "Saturday",
        "mealType": "dinner",
        "amount": 0,
        "unit": "",
        "meal": "Borscht with sour cream"
      }
    ]
  }
}